README.md
sasin.py
setup.py
sasin.egg-info/PKG-INFO
sasin.egg-info/SOURCES.txt
sasin.egg-info/dependency_links.txt
sasin.egg-info/not-zip-safe
sasin.egg-info/top_level.txt